README.md
setup.py
mc_signal.egg-info/PKG-INFO
mc_signal.egg-info/SOURCES.txt
mc_signal.egg-info/dependency_links.txt
mc_signal.egg-info/top_level.txt
src/__init__.py
src/client.py
src/mc_event.py
src/mc_signal.py
src/server.py