Metadata-Version: 1.0
Name: mc-signal
Version: 0.1.0
Summary: The MC signal library
Home-page: UNKNOWN
Author: Kalle Bracht
Author-email: UNKNOWN
License: MIT
Platform: UNKNOWN
